jarviscore/__init__.py
jarviscore/__main__.py
jarviscore/bridge.py
jarviscore/channel.py
jarviscore/client.py
jarviscore/errors.py
jarviscore/helpers.py
jarviscore/httpclient.py
jarviscore/log.py
jarviscore/message.py
jarviscore/messageparser.py
jarviscore/model.py
jarviscore/module.py
jarviscore/settings.py
jarviscore/socket.py
jarviscore/telemetry.py
jarviscore/user.py
jarviscore/modules/__init__.py
jarviscore/modules/connections.py
jarviscore/modules/creator.py
jarviscore/modules/ping.py
jarviscore/modules/subs.py
jarviscore/modules/uptime.py
jarviscore_nightly-0.1.1.203.dist-info/METADATA
jarviscore_nightly-0.1.1.203.dist-info/WHEEL
jarviscore_nightly-0.1.1.203.dist-info/top_level.txt
jarviscore_nightly-0.1.1.203.dist-info/RECORD
