Metadata-Version: 2.1
Name: jarviscore-nightly
Version: 0.1.1.203
Summary: A python package for creating Twitch Bots (Nightly Build)
Home-page: https://dev.azure.com/cubbei/jarviscore
Author: Cubbei
Author-email: cubbei@outlook.com
License: GPL
Platform: UNKNOWN
Classifier: Programming Language :: Python :: 3
Classifier: Programming Language :: Python :: 3.6
Classifier: Programming Language :: Python :: 3.7
Classifier: Programming Language :: Python :: 3.8
Classifier: License :: OSI Approved :: GNU General Public License v3 or later (GPLv3+)
Classifier: Operating System :: OS Independent
Requires-Python: >=3.6
Requires-Dist: PyMySQL
Requires-Dist: PyYAML
Requires-Dist: requests
